MANIFEST.in
README.rst
setup.py
vacation/__init__.py
vacation/command_line.py
vacation/lexer.py
vacation/rc.py
vacation/transactions.py
vacation/vacation.py
vacation.egg-info/PKG-INFO
vacation.egg-info/SOURCES.txt
vacation.egg-info/dependency_links.txt
vacation.egg-info/entry_points.txt
vacation.egg-info/not-zip-safe
vacation.egg-info/requires.txt
vacation.egg-info/top_level.txt