Metadata-Version: 1.1
Name: vacation
Version: 0.4
Summary: Track your vacation days.
Home-page: https://github.com/pulseenergy/vacation
Author: Enernoc
Author-email: supermitch@gmail.com
License: GPL2
Platform: UNKNOWN
Classifier: Development Status :: 4 - Beta
Classifier: Environment :: Console
Classifier: Intended Audience :: Developers
Classifier: License :: OSI Approved :: GNU General Public License v2 (GPLv2)
Classifier: Natural Language :: English
Classifier: Operating System :: OS Independent
Classifier: Programming Language :: Python :: 2.7
Classifier: Topic :: Utilities
